README
setup.py
pypjlink/__init__.py
pypjlink/cli.py
pypjlink/cliutils.py
pypjlink/projector.py
pypjlink/protocol.py
pypjlink.egg-info/PKG-INFO
pypjlink.egg-info/SOURCES.txt
pypjlink.egg-info/dependency_links.txt
pypjlink.egg-info/entry_points.txt
pypjlink.egg-info/requires.txt
pypjlink.egg-info/top_level.txt
pypjlink/tests/__init__.py
pypjlink/tests/test_projector.py
pypjlink/tests/utils.py