Metadata-Version: 1.1
Name: pypjlink
Version: 1.1
Summary: PJLink is a standard for controlling data projectors.
Home-page: https://github.com/gaetano-guerriero/pypjlink
Author: Peter Ward <peteraward@gmail.com>, Gaetano Guerriero <gaetano.guerriero@spacespa.it>
Author-email: gaetano.guerriero@spacespa.it
License: UNKNOWN
Platform: UNKNOWN
Classifier: Development Status :: 5 - Production/Stable
Classifier: Environment :: Console
Classifier: License :: OSI Approved :: Apache Software License
Classifier: Natural Language :: English
Classifier: Topic :: Multimedia :: Video :: Display
Classifier: Topic :: Utilities
